{"colors":[{"code":"RV-189","title":" Ipanema Yellow","color":"#fff9c3"},{"code":"RV-20","title":" Party Yellow","color":"#ffef8c"},{"code":"RV-109","title":" Canarias Yellow","color":"#fff058"},{"code":"RV-1021","title":" Light Yellow","color":"#fedf00"},{"code":"RV-110","title":" Yosemite Yellow","color":"#c7b300"},{"code":"RV-111","title":" Babel Green","color":"#a29400"},{"code":"RV-112","title":" Mission Green","color":"#766a10"},{"code":"RV-113","title":" Dragon Green","color":"#5e5003"},{"code":"RV-114","title":" Maya Green","color":"#3d3408"},{"code":"RV-192","title":" Sundance","color":"#ffebc2"},{"code":"RV-102","title":" Dalai Orange","color":"#fddca3"},{"code":"RV-103","title":" Plural Orange","color":"#fac67e"},{"code":"RV-50","title":" Solar Orange","color":"#f7b060"},{"code":"RV-105","title":" Tangerine","color":"#f5a54a"},{"code":"RV-106","title":" Lava Orange","color":"#ef8407"},{"code":"RV-2004","title":" Kalani Orange","color":"#ea640d"},{"code":"RV-107","title":" Mars Orange","color":"#e64715"},{"code":"RV-108","title":" Phoenix Orange","color":"#be3819"},{"code":"RV-190","title":" Malta White","color":"#f9f6e9"},{"code":"RV-1013","title":" Bone White","color":"#f3efd6"},{"code":"RV-135","title":" Safari Brown","color":"#eadfa8"},{"code":"RV-136","title":" Inca Brown","color":"#d9b365"},{"code":"RV-137","title":" Kraft Brown","color":"#bd9b61"},{"code":"RV-139","title":" Sequoia Brown","color":"#6f5229"},{"code":"RV-138","title":" Marrakech","color":"#99743f"},{"code":"RV-140","title":" Mole Brown","color":"#503915"},{"code":"RV-141","title":" Gondola Brown","color":"#412c13"},{"code":"RV-191","title":" Jaima Brown","color":"#f1e8de"},{"code":"RV-94","title":" Dingo Brown","color":"#e8d0b7"},{"code":"RV-95","title":" Tana Brown","color":"#d2a785"},{"code":"RV-96","title":" Montserrat","color":"#cc955e"},{"code":"RV-97","title":" Chiapas Brown","color":"#a0682b"},{"code":"RV-98","title":" Bean Brown","color":"#a65f2f"},{"code":"RV-100","title":" Coffee Brown","color":"#402009"},{"code":"RV-35","title":" Chocolate Brown","color":"#41302a"},{"code":"RV-101","title":" Ebony Brown","color":"#2f1109"},{"code":"RV-193","title":" Chewing Gum","color":"#f6c3d3"},{"code":"RV-115","title":" Tutti Frutti","color":"#ea949d"},{"code":"RV-3017","title":" Fever Red","color":"#dc534d"},{"code":"RV-116","title":" Blood Red","color":"#d52f25"},{"code":"RV-3001","title":" Vivid Red","color":"#b3061e"},{"code":"RV-47","title":" Clandestine Red","color":"#950825"},{"code":"RV-3004","title":" Bordeaux Red","color":"#610819"},{"code":"RV-3007","title":" Cherokee Red","color":"#3a0807"},{"code":"RV-77","title":" Night Red","color":"#2d0604"},{"code":"RV-194","title":" Supernova Pink","color":"#fce6eb"},{"code":"RV-164","title":" Tokyo Pink","color":"#f7c7d7"},{"code":"RV-165","title":" Orchid Pink","color":"#ec7faa"},{"code":"RV-4003","title":" Erika","color":"#e85b99"},{"code":"RV-4010","title":" Magenta","color":"#d90075"},{"code":"RV-166","title":" Açai Red","color":"#9a004b"},{"code":"RV-167","title":" Rioja Red","color":"#6b0037"},{"code":"RV-168","title":" Anger Red","color":"#550026"},{"code":"RV-169","title":" Taurus Red","color":"#36001c"},{"code":"RV-196","title":" Saudade Pink","color":"#f2dddd"},{"code":"RV-86","title":" Boreal Pink","color":"#e3bfc3"},{"code":"RV-87","title":" Stereo Pink","color":"#ca95a4"},{"code":"RV-88","title":" Single Pink","color":"#a06c7e"},{"code":"RV-89","title":" Compact Red","color":"#864a54"},{"code":"RV-90","title":" Bitacora Red","color":"#582b3a"},{"code":"RV-91","title":" Pandora Red","color":"#4f1f30"},{"code":"RV-92","title":" Gaudi Red","color":"#321129"},{"code":"RV-93","title":" Stendhal Red","color":"#1e000e"},{"code":"RV-197","title":" Penelope Brown","color":"#f8ede7"},{"code":"RV-176","title":" Sensible Brown","color":"#efd9d0"},{"code":"RV-203","title":" Oak Brown","color":"#a86059"},{"code":"RV-204","title":" Interrail Brown","color":"#9f3d44"},{"code":"RV-205","title":" Warrior Brown","color":"#5a1521"},{"code":"RV-200","title":" Plancton","color":"#e8d6c8"},{"code":"RV-64","title":" Respect Pink","color":"#b59892"},{"code":"RV-201","title":" Scarlet Brown","color":"#8e6061"},{"code":"RV-202","title":" Mosquito Brown","color":"#684445"},{"code":"RV-321","title":" April Violet","color":"#e9cde4"},{"code":"RV-195","title":" Shiva Violet","color":"#e5cce1"},{"code":"RV-322","title":" Arlet Violet","color":"#d0add2"},{"code":"RV-170","title":" Persia Violet","color":"#c5add0"},{"code":"RV-323","title":" Mandala Violet","color":"#bc90c1"},{"code":"RV-276","title":" Bishop Violet","color":"#c29bcb"},{"code":"RV-275","title":" Raval Violet","color":"#94679c"},{"code":"RV-283","title":" Sultan Violet","color":"#83577d"},{"code":"RV-274","title":" Reverend Violet","color":"#6c5d80"},{"code":"RV-310","title":" Republic Violet","color":"#dacbe5"},{"code":"RV-311","title":" Woodstock Violet","color":"#cdc3e1"},{"code":"RV-171","title":" Community Violet","color":"#b194c0"},{"code":"RV-172","title":" Destiny Violet","color":"#8270a3"},{"code":"RV-173","title":" Ultraviolet","color":"#6b4d8d"},{"code":"RV-174","title":" Venus Violet","color":"#483366"},{"code":"RV-175","title":" Electra Violet","color":"#32234e"},{"code":"RV-28","title":" Cosmos Violet","color":"#241c46"},{"code":"RV-27","title":" Vampire Violet","color":"#140632"},{"code":"RV-312","title":" Sagan Blue","color":"#c1cae8"},{"code":"RV-313","title":" Martinez Blue","color":"#aebee3"},{"code":"RV-314","title":" Rosemary Blue","color":"#9db1dc"},{"code":"RV-315","title":" Dancer Blue","color":"#85a0d3"},{"code":"RV-316","title":" Marsellie Blue","color":"#6386c3"},{"code":"RV-317","title":" Porto Blue","color":"#616cb1"},{"code":"RV-318","title":" Ween Blue","color":"#3b54a1"},{"code":"RV-319","title":" Tuareg Blue","color":"#263284"},{"code":"RV-320","title":" Mantra Blue","color":"#302b66"},{"code":"RV-184","title":" Rain Blue","color":"#c4e7f8"},{"code":"RV-149","title":" Hydra Blue","color":"#8ecae5"},{"code":"RV-150","title":" Argo Blue","color":"#44b3df"},{"code":"RV-151","title":" Freedom Blue","color":"#0098d2"},{"code":"RV-152","title":" Europe Blue","color":"#0074b0"},{"code":"RV-30","title":" Electric Blue","color":"#005891"},{"code":"RV-5005","title":" Dark Blue","color":"#003875"},{"code":"RV-154","title":" Twister Blue","color":"#042151"},{"code":"RV-5013","title":" Navy Blue","color":"#010e30"},{"code":"RV-185","title":" Angel Blue","color":"#eaf0f5"},{"code":"RV-156","title":" Barceloneta Blue","color":"#cae4f0"},{"code":"RV-157","title":" Thalassa Blue","color":"#a2d3ea"},{"code":"RV-158","title":" Perseus Blue","color":"#7fb8d5"},{"code":"RV-159","title":" Odyssey Blue","color":"#6ea4be"},{"code":"RV-160","title":" Eureka Blue","color":"#467289"},{"code":"RV-161","title":" Jase Blue","color":"#2e4a5b"},{"code":"RV-162","title":" Deep Blue","color":"#003447"},{"code":"RV-163","title":" Poseydon Blue","color":"#00202c"},{"code":"RV-186","title":" Virgin Green","color":"#f5faf7"},{"code":"RV-142","title":" Gemini Green","color":"#e1f0e8"},{"code":"RV-6027","title":" Luminous  Green","color":"#a1d5cf"},{"code":"RV-144","title":" Bali Green","color":"#7bc6c0"},{"code":"RV-145","title":" Erasmus Green","color":"#5bb5b5"},{"code":"RV-5018","title":" Turquoise","color":"#008691"},{"code":"RV-146","title":" Glory Blue","color":"#2d6a75"},{"code":"RV-147","title":" Pegasus Blue","color":"#003640"},{"code":"RV-148","title":" Hercules Blue","color":"#002628"},{"code":"RV-187","title":" Vespa Green","color":"#f1f5df"},{"code":"RV-124","title":" Frisco Green","color":"#d4e19e"},{"code":"RV-16","title":" Pistachio Green","color":"#bdd268"},{"code":"RV-125","title":" Neon Green","color":"#a5b700"},{"code":"RV-34","title":" Guacamole Green","color":"#81a512"},{"code":"RV-6018","title":" Valley Green","color":"#4a7518"},{"code":"RV-126","title":" Toscana Green","color":"#2b491e"},{"code":"RV-127","title":" Era Green","color":"#142f0f"},{"code":"RV-6009","title":" Amazon Green","color":"#0f2405"},{"code":"RV-188","title":" Shining Green","color":"#f2edbe"},{"code":"RV-1016","title":" Lemon Yellow","color":"#dcd872"},{"code":"RV-129","title":" Oregano Green","color":"#afab00"},{"code":"RV-60","title":" Krypton Green","color":"#83890e"},{"code":"RV-130","title":" Euskadi Green","color":"#50590d"},{"code":"RV-131","title":" Comarca Green","color":"#333b08"},{"code":"RV-132","title":" Borneo Green","color":"#283307"},{"code":"RV-133","title":" Dharma Green","color":"#1e2705"},{"code":"RV-134","title":" Infinite Green","color":"#131c04"},{"code":"RV-270","title":" Formentera Blue","color":"#00b4bc"},{"code":"RV-269","title":" Genesis Blue","color":"#179dab"},{"code":"RV-268","title":" Tramontana Blue","color":"#007788"},{"code":"RV-199","title":" Java Green","color":"#86c8b4"},{"code":"RV-182","title":" Emerald Green","color":"#009e8f"},{"code":"RV-183","title":" Beryl Green","color":"#117774"},{"code":"RV-179","title":" Bonsai Green","color":"#b8bb86"},{"code":"RV-180","title":" Thai Green","color":"#8e966e"},{"code":"RV-181","title":" Labyrinth Green","color":"#47492b"},{"code":"RV-267","title":" Sulfur Yellow","color":"#faeb37"},{"code":"RV-266","title":" Psycho Green","color":"#d5e739"},{"code":"RV-265","title":" Sónar Green","color":"#b9be56"},{"code":"RV-281","title":" Laser Green","color":"#99c221"},{"code":"RV-282","title":" Laos Green","color":"#8fcb24"},{"code":"RV-280","title":" Hulk Green","color":"#41a248"},{"code":"RV-272","title":" Mint Green","color":"#29cb7e"},{"code":"RV-273","title":" Iguana Green","color":"#8cc947"},{"code":"RV-271","title":" Mystic Green","color":"#25bd59"},{"code":"RV-1017","title":" Peach","color":"#e6a65d"},{"code":"RV-1028","title":" Medium Yellow","color":"#ffa300"},{"code":"RV-207","title":" Mango","color":"#e87722"},{"code":"RV-177","title":" Eldorado","color":"#f1c700"},{"code":"RV-178","title":" Tibet","color":"#d58b26"},{"code":"RV-8023","title":" Mustard","color":"#a76225"},{"code":"RV-99","title":" Glace Brown","color":"#7a3d24"},{"code":"RV-278","title":" Joker pink","color":"#e44c9a"},{"code":"RV-277","title":" Disco Pink","color":"#bd51a2"},{"code":"RV-279","title":" Rosario Pink","color":"#dc4588"},{"code":"RV-3020","title":" Light Red","color":"#ef3a38"},{"code":"RV-241","title":" Madrid Red","color":"#f65058"},{"code":"RV-245","title":" Cyan","color":"#00ffff"},{"code":"RV-243","title":" Babylon Blue","color":"#3d5588"},{"code":"RV-198","title":" Stardust Grey","color":"#eef0f1"},{"code":"RV-7047","title":" Siberian Grey","color":"#dbdddf"},{"code":"RV-118","title":" Rita Grey","color":"#cdd0d1"},{"code":"R-7040","title":" Pearl Grey","color":"#b5b8ba"},{"code":"RV-119","title":" London Grey","color":"#898b8e"},{"code":"RV-120","title":" Wolf Grey","color":"#5b5b5e"},{"code":"RV-121","title":" Icarus Grey","color":"#48484b"},{"code":"RV-7016","title":" Anthracite Grey","color":"#363538"},{"code":"RV-78","title":" Metropolis Grey","color":"#262227"},{"code":"RV-300","title":" Tofu Grey","color":"#fef9e3"},{"code":"RV-301","title":" Placebo Grey","color":"#f5efd6"},{"code":"RV-302","title":" Koala Grey","color":"#d8cdc3"},{"code":"RV-303","title":" Native Grey","color":"#bcb2ad"},{"code":"RV-304","title":" Balboa Grey","color":"#a29690"},{"code":"RV-305","title":" Cloud Grey","color":"#c9d2d7"},{"code":"RV-306","title":" Winter Grey","color":"#b7c1cd"},{"code":"RV-307","title":" Jaws Grey","color":"#abb5c1"},{"code":"RV-308","title":" Whale Grey","color":"#6b7c91"},{"code":"RV-309","title":" Chernobyl Grey","color":"#5e7386"},{"code":"R-9010","title":" White","color":"#ffffff"},{"code":"R-9011","title":" Black","color":"#000000"},{"code":"-","title":"Fluorescent Yellow","color":"#fdef4c"},{"code":"-","title":"Fluorescent Orange","color":"#f68b1f"},{"code":"-","title":"Fluorescent Red","color":"#ef3a4d"},{"code":"-","title":"Fluorescent Fuchsia","color":"#ee4d9b"},{"code":"-","title":"Fluorescent Violet","color":"#9857a5"},{"code":"-","title":"Fluorescent Blue","color":"#008dd2"},{"code":"-","title":"Fluorescent Green","color":"#61bb46"},{"code":"-","title":"Spectral Ethereal Yellow","color":"#fffaa3"},{"code":"-","title":"Spectral Calima Orange","color":"#fbb36d"},{"code":"-","title":"Spectral Soul Red","color":"#eda795"},{"code":"-","title":"Spectral Judea Brown","color":"#b79e74"},{"code":"-","title":"Spectral Aura Violet","color":"#c5add0"},{"code":"-","title":"Spectral Atmosphere Blue","color":"#afccdf"},{"code":"-","title":"Spectral Breeze Green","color":"#a1d5cf"},{"code":"-","title":"Spectral Air White","color":"#ffffff"},{"code":"-","title":"Spectral Smoke Grey","color":"#cdcdcd"},{"code":"-","title":"Spectral Shadow Black","color":"#a6a6a7"}]}